test
wellview_odata_api
