Metadata-Version: 2.1
Name: wellview-odata-api
Version: 1.0.0
Summary: OData Service for namespace Default
Home-page: 
Author-email: 
License: UNKNOWN
Keywords: Swagger,OData Service for namespace Default
Platform: UNKNOWN
